{ "articles": [
  { "author": ["Herbert Vander Lugt","herbertvanderlugt"],
    "categories": [["Archives","christian-life/archives-christian-life/"],["Christian Life","christian-life/"]],
    "date": [2001,7,31],
    "passage": "Acts 7:54-60",
    "quote": "1 Peter 1:3",
    "tags": [],
    "title": "Beyond Calm Acceptance",
    "url": "http://odb.org/2001/07/31/beyond-calm-acceptance/"
  }, 
  { "author": ["Joanie Yoder","joanieyoder"],
    "categories": [["Archives","christian-life/archives-christian-life/"],["Christian Life","christian-life/"]],
    "date": [2001,7,30],
    "passage": "1 John 3:16-24",
    "quote": "1 John 3:18",
    "tags": [],
    "title": "What Makes You Tick?",
    "url": "http://odb.org/2001/07/30/what-makes-you-tick/"
  }, 
  { "author": ["Mart De Haan","martdehaan"],
    "categories": [["Archives","christian-life/archives-christian-life/"],["Christian Life","christian-life/"]],
    "date": [2001,7,29],
    "passage": "Isaiah 51:1-16",
    "quote": "Isaiah 51:12",
    "tags": [],
    "title": "What Do You Fear?",
    "url": "http://odb.org/2001/07/29/what-do-you-fear-2/"
  }, 
  { "author": ["Richard De Haan","richarddehaan"],
    "categories": [["Archives","christian-life/archives-christian-life/"],["Christian Life","christian-life/"]],
    "date": [2001,7,28],
    "passage": "Proverbs 3:1-6",
    "quote": "Proverbs 3:5-6",
    "tags": [],
    "title": "Directions From Above",
    "url": "http://odb.org/2001/07/28/directions-from-above/"
  }, 
  { "author": ["Haddon W. Robinson","haddonwrobinson"],
    "categories": [["Archives","christian-life/archives-christian-life/"],["Christian Life","christian-life/"]],
    "date": [2001,7,27],
    "passage": "Matthew 26:6-13",
    "quote": "Matthew 26:13",
    "tags": [],
    "title": "Appreciated",
    "url": "http://odb.org/2001/07/27/the-appreciated-2/"
  }, 
  { "author": ["Mart De Haan","martdehaan"],
    "categories": [["Archives","christian-life/archives-christian-life/"],["Christian Life","christian-life/"]],
    "date": [2001,7,26],
    "passage": "Luke 15:11-32",
    "quote": "Luke 15:32",
    "tags": [],
    "title": "What Makes You Happy?",
    "url": "http://odb.org/2001/07/26/what-makes-you-happy/"
  }, 
  { "author": ["David C. McCasland","davidcmccasland"],
    "categories": [["Archives","christian-life/archives-christian-life/"],["Christian Life","christian-life/"]],
    "date": [2001,7,25],
    "passage": "1 Timothy 6:6-19",
    "quote": "1 Timothy 6:18",
    "tags": [],
    "title": "Profit Sharing",
    "url": "http://odb.org/2001/07/25/profit-sharing/"
  }, 
  { "author": ["Vernon C. Grounds","vernongrounds"],
    "categories": [["Archives","christian-life/archives-christian-life/"],["Christian Life","christian-life/"]],
    "date": [2001,7,24],
    "passage": "Psalm 77:1-15",
    "quote": "Psalm 77:7",
    "tags": [],
    "title": "'God Hides His Face'",
    "url": "http://odb.org/2001/07/24/god-hides-his-face/"
  }, 
  { "author": ["Dennis J. De Haan","dennisjdehaan"],
    "categories": [["Archives","christian-life/archives-christian-life/"],["Christian Life","christian-life/"]],
    "date": [2001,7,23],
    "passage": "Mark 12:28-34",
    "quote": "Mark 12:31",
    "tags": [],
    "title": "Driving Lessons",
    "url": "http://odb.org/2001/07/23/driving-lessons/"
  }, 
  { "author": ["David C. Egner","davidcegner"],
    "categories": [["Archives","christian-life/archives-christian-life/"],["Christian Life","christian-life/"]],
    "date": [2001,7,22],
    "passage": "Matthew 21:12-17",
    "quote": "Matthew 21:16",
    "tags": [],
    "title": "The Faith Of A Child",
    "url": "http://odb.org/2001/07/22/the-faith-of-a-child/"
  }, 
  { "author": ["Herbert Vander Lugt","herbertvanderlugt"],
    "categories": [["Archives","christian-life/archives-christian-life/"],["Christian Life","christian-life/"]],
    "date": [2001,7,21],
    "passage": "Mark 12:41-44",
    "quote": "2 Corinthians 8:12",
    "tags": [],
    "title": "Am I Willing?",
    "url": "http://odb.org/2001/07/21/am-i-willing/"
  }, 
  { "author": ["Dave Branon","davebranon"],
    "categories": [["Archives","christian-life/archives-christian-life/"],["Christian Life","christian-life/"]],
    "date": [2001,7,20],
    "passage": "Luke 16:19-31",
    "quote": "2 Corinthians 6:2",
    "tags": [],
    "title": "Are You Ready?",
    "url": "http://odb.org/2001/07/20/are-you-ready-5/"
  }, 
  { "author": ["Joanie Yoder","joanieyoder"],
    "categories": [["Archives","christian-life/archives-christian-life/"],["Christian Life","christian-life/"]],
    "date": [2001,7,19],
    "passage": "Zechariah 4:1-14",
    "quote": "Zechariah 4:10",
    "tags": [],
    "title": "The Power Of Small Deeds",
    "url": "http://odb.org/2001/07/19/the-power-of-small-deeds/"
  }, 
  { "author": ["Haddon W. Robinson","haddonwrobinson"],
    "categories": [["Archives","christian-life/archives-christian-life/"],["Christian Life","christian-life/"]],
    "date": [2001,7,18],
    "passage": "Luke 11:1-10",
    "quote": "Luke 11:1",
    "tags": [],
    "title": "A Prayer Jesus Never Prayed",
    "url": "http://odb.org/2001/07/18/a-prayer-jesus-never-prayed/"
  }, 
  { "author": ["Vernon C. Grounds","vernongrounds"],
    "categories": [["Archives","christian-life/archives-christian-life/"],["Christian Life","christian-life/"]],
    "date": [2001,7,17],
    "passage": "Ephesians 6:10-18",
    "quote": "Matthew 26:41",
    "tags": [],
    "title": "My Achilles Heel",
    "url": "http://odb.org/2001/07/17/my-achilles-heel/"
  }, 
  { "author": ["David C. McCasland","davidcmccasland"],
    "categories": [["Archives","christian-life/archives-christian-life/"],["Christian Life","christian-life/"]],
    "date": [2001,7,16],
    "passage": "Acts 20:17-32",
    "quote": "Acts 20:24",
    "tags": [],
    "title": "Life Wish",
    "url": "http://odb.org/2001/07/16/life-wish/"
  }, 
  { "author": ["Mart De Haan","martdehaan"],
    "categories": [["Archives","christian-life/archives-christian-life/"],["Christian Life","christian-life/"]],
    "date": [2001,7,15],
    "passage": "Romans 12:3-8",
    "quote": "Romans 12:6",
    "tags": [],
    "title": "The Right Fit",
    "url": "http://odb.org/2001/07/15/the-right-fit/"
  }, 
  { "author": ["Herbert Vander Lugt","herbertvanderlugt"],
    "categories": [["Archives","christian-life/archives-christian-life/"],["Christian Life","christian-life/"]],
    "date": [2001,7,14],
    "passage": "Acts 17:10-15",
    "quote": "Acts 17:11",
    "tags": [],
    "title": "For Honest Skeptics",
    "url": "http://odb.org/2001/07/14/for-honest-skeptics/"
  }, 
  { "author": ["David C. Egner","davidcegner"],
    "categories": [["Archives","christian-life/archives-christian-life/"],["Christian Life","christian-life/"]],
    "date": [2001,7,13],
    "passage": "Acts 16:6-12",
    "quote": "Acts 16:6",
    "tags": [],
    "title": "Frustrated Plans",
    "url": "http://odb.org/2001/07/13/frustrated-plans/"
  }, 
  { "author": ["Albert Lee","albertlee"],
    "categories": [["Archives","christian-life/archives-christian-life/"],["Christian Life","christian-life/"]],
    "date": [2001,7,12],
    "passage": "Haggai 1:1-13",
    "quote": "Haggai 1:2",
    "tags": [],
    "title": "Right Timing",
    "url": "http://odb.org/2001/07/12/right-timing/"
  }, 
  { "author": ["Dennis J. De Haan","dennisjdehaan"],
    "categories": [["Archives","christian-life/archives-christian-life/"],["Christian Life","christian-life/"]],
    "date": [2001,7,11],
    "passage": "Deuteronomy 29:10-29",
    "quote": "Deuteronomy 29:29",
    "tags": [],
    "title": "Secrets",
    "url": "http://odb.org/2001/07/11/secrets/"
  }, 
  { "author": ["Joanie Yoder","joanieyoder"],
    "categories": [["Archives","christian-life/archives-christian-life/"],["Christian Life","christian-life/"]],
    "date": [2001,7,10],
    "passage": "Romans 6:11-23",
    "quote": "John 8:36",
    "tags": [],
    "title": "Sinful Habits Can Be Broken",
    "url": "http://odb.org/2001/07/10/sinful-habits-can-be-broken/"
  }, 
  { "author": ["Dave Branon","davebranon"],
    "categories": [["Archives","christian-life/archives-christian-life/"],["Christian Life","christian-life/"]],
    "date": [2001,7,9],
    "passage": "Psalm 142:1-7",
    "quote": "Psalm 142:6",
    "tags": [],
    "title": "Cries Of Desperation",
    "url": "http://odb.org/2001/07/09/cries-of-desperation/"
  }, 
  { "author": ["Vernon C. Grounds","vernongrounds"],
    "categories": [["Archives","christian-life/archives-christian-life/"],["Christian Life","christian-life/"]],
    "date": [2001,7,8],
    "passage": "John 17:1-26",
    "quote": "John 17:16",
    "tags": [],
    "title": "A Balanced Attitude",
    "url": "http://odb.org/2001/07/08/a-balanced-attitude/"
  }, 
  { "author": ["Richard De Haan","richarddehaan"],
    "categories": [["Archives","christian-life/archives-christian-life/"],["Christian Life","christian-life/"]],
    "date": [2001,7,7],
    "passage": "1 Thessalonians 5:12-22",
    "quote": "1 Thessalonians 5:14",
    "tags": [],
    "title": "Friend Or Foe?",
    "url": "http://odb.org/2001/07/07/friend-or-foe/"
  }, 
  { "author": ["Herbert Vander Lugt","herbertvanderlugt"],
    "categories": [["Archives","christian-life/archives-christian-life/"],["Christian Life","christian-life/"]],
    "date": [2001,7,6],
    "passage": "John 16:5-16",
    "quote": "John 16:15",
    "tags": [],
    "title": "The Loner",
    "url": "http://odb.org/2001/07/06/the-loner/"
  }, 
  { "author": ["Vernon C. Grounds","vernongrounds"],
    "categories": [["Archives","christian-life/archives-christian-life/"],["Christian Life","christian-life/"]],
    "date": [2001,7,5],
    "passage": "Luke 10:30-37",
    "quote": "Titus 3:14",
    "tags": [],
    "title": "Exercise Your Right",
    "url": "http://odb.org/2001/07/05/exercise-your-right/"
  }, 
  { "author": ["Dave Branon","davebranon"],
    "categories": [["Archives","christian-life/archives-christian-life/"],["Christian Life","christian-life/"]],
    "date": [2001,7,4],
    "passage": "Psalm 66:1-8",
    "quote": "Psalm 66:1-2",
    "tags": [],
    "title": "Celebrate Together",
    "url": "http://odb.org/2001/07/04/celebrate-together/"
  }, 
  { "author": ["David C. McCasland","davidcmccasland"],
    "categories": [["Archives","christian-life/archives-christian-life/"],["Christian Life","christian-life/"]],
    "date": [2001,7,3],
    "passage": "Hebrews 4:11-16",
    "quote": "Hebrews 4:12",
    "tags": [],
    "title": "The Big Questions",
    "url": "http://odb.org/2001/07/03/the-big-questions/"
  }, 
  { "author": ["Joanie Yoder","joanieyoder"],
    "categories": [["Archives","christian-life/archives-christian-life/"],["Christian Life","christian-life/"]],
    "date": [2001,7,2],
    "passage": "Ephesians 3:8-21",
    "quote": "Ephesians 3:11-12",
    "tags": [],
    "title": "He's Waiting",
    "url": "http://odb.org/2001/07/02/hes-waiting-2/"
  }, 
  { "author": ["David C. Egner","davidcegner"],
    "categories": [["Archives","christian-life/archives-christian-life/"],["Christian Life","christian-life/"]],
    "date": [2001,7,1],
    "passage": "Acts 4:5-12",
    "quote": "John 14:6",
    "tags": [],
    "title": "River Of Disappointment",
    "url": "http://odb.org/2001/07/01/river-of-disappointment/"
  }
],
"month": 7,
"year": 2001
}