{ "articles": [
  { "author": ["Bill Crowder","billcrowder"],
    "categories": [["Archives","christian-life/archives-christian-life/"],["Basics Of Faith","basics-of-faith/"],["Christian Life","christian-life/"],["God","basics-of-faith/god-basics-of-faith/"],["Relating To God","relationships/relating-to-god-relationships/"]],
    "date": [2010,11,30],
    "passage": "1 Corinthians 15:1-11",
    "quote": "1 Corinthians 15:3-4",
    "tags": [["cross","cross"],["grace","grace"],["Jesus Christ","jesus-christ"],["salvation","salvation"],["sin","sin-christian-life"]],
    "title": "Would Or Did?",
    "url": "http://odb.org/2010/11/30/would-or-did/"
  }, 
  { "author": ["Dennis Fisher","dennisfisher"],
    "categories": [["Archives","christian-life/archives-christian-life/"],["Attitudes","christian-life/attitudes-christian-life/"],["Christian Life","christian-life/"],["Personal Crisis","christian-life/personal-crisis-christian-life/"],["Relating To God","relationships/relating-to-god-relationships/"]],
    "date": [2010,11,29],
    "passage": "Exodus 4:1-5",
    "quote": "Exodus 4:2",
    "tags": [["anxiety","anxiety"],["future","future"],["guidance","guidance"],["leading","leading"],["service","service"]],
    "title": "What Is In Your Hand?",
    "url": "http://odb.org/2010/11/29/what-is-in-your-hand/"
  }, 
  { "author": ["Joe Stowell","joestowell"],
    "categories": [["Archives","christian-life/archives-christian-life/"],["Attitudes","christian-life/attitudes-christian-life/"],["Christian Life","christian-life/"],["Relating To God","relationships/relating-to-god-relationships/"]],
    "date": [2010,11,28],
    "passage": "Matthew 6:19-21",
    "quote": "Matthew 6:19-20",
    "tags": [["eternity","eternity"],["faithfulness","faithfulness"],["money","money"],["possessions","possessions"],["riches","riches"]],
    "title": "A Collector’s Heaven",
    "url": "http://odb.org/2010/11/28/a-collector%e2%80%99s-heaven/"
  }, 
  { "author": ["Dave Branon","davebranon"],
    "categories": [["Archives","christian-life/archives-christian-life/"],["Attitudes","christian-life/attitudes-christian-life/"],["Basics Of Faith","basics-of-faith/"],["Christian Life","christian-life/"],["Personal Crisis","christian-life/personal-crisis-christian-life/"]],
    "date": [2010,11,27],
    "passage": "2 Corinthians 5:6-8; Philippians 1:21-23",
    "quote": "2 Corinthians 6:2",
    "tags": [["death","death"],["eternity","eternity"],["heaven","heaven"],["salvation","salvation"],["suffering","suffering"]],
    "title": "Ernie’s Farewell",
    "url": "http://odb.org/2010/11/27/ernie%e2%80%99s-farewell/"
  }, 
  { "author": ["Philip Yancey","philipyancey"],
    "categories": [["Archives","christian-life/archives-christian-life/"],["Basics Of Faith","basics-of-faith/"],["Christian Life","christian-life/"],["Relating To God","relationships/relating-to-god-relationships/"]],
    "date": [2010,11,26],
    "passage": "Psalm 27",
    "quote": "Psalm 27:1",
    "tags": [["expressions of","expressions-of"],["fellowship","fellowship"],["praise","praise"],["presence","presence"],["worship","worship"]],
    "title": "Advanced School",
    "url": "http://odb.org/2010/11/26/advanced-school/"
  }, 
  { "author": ["David C. McCasland","davidcmccasland"],
    "categories": [["Archives","christian-life/archives-christian-life/"],["Attitudes","christian-life/attitudes-christian-life/"],["Christian Life","christian-life/"],["Relating To God","relationships/relating-to-god-relationships/"]],
    "date": [2010,11,25],
    "passage": "Proverbs 3:1-12",
    "quote": "Proverbs 3:5",
    "tags": [["contentment","contentment"],["gratitude","gratitude"],["thankfulness","thankfulness"]],
    "title": "We Thank The Lord",
    "url": "http://odb.org/2010/11/25/we-thank-the-lord/"
  }, 
  { "author": ["Julie Ackerman Link","julieackermanlink"],
    "categories": [["Archives","christian-life/archives-christian-life/"],["Character","christian-life/character-christian-life/"],["Christian Life","christian-life/"],["Relating To God","relationships/relating-to-god-relationships/"]],
    "date": [2010,11,24],
    "passage": "Luke 7:11-23",
    "quote": "Malachi 4:2",
    "tags": [["Christ's return","christs-return"],["comfort","comfort"],["hope","hope"],["restoration","restoration"]],
    "title": "Restoring Order",
    "url": "http://odb.org/2010/11/24/restoring-order/"
  }, 
  { "author": ["Cindy Hess Kasper","cindyhesskasper"],
    "categories": [["Archives","christian-life/archives-christian-life/"],["Christian Life","christian-life/"],["Personal Crisis","christian-life/personal-crisis-christian-life/"],["Relating To God","relationships/relating-to-god-relationships/"]],
    "date": [2010,11,23],
    "passage": "Ephesians 2:11-22",
    "quote": "Ephesians 2:18",
    "tags": [["father","father"],["fellowship","fellowship"],["Holy Spirit","holy-spirit"],["prayer","prayer"],["presence","presence"]],
    "title": "Unlimited Access",
    "url": "http://odb.org/2010/11/23/unlimited-access/"
  }, 
  { "author": ["Anne Cetas","annecetas"],
    "categories": [["Archives","christian-life/archives-christian-life/"],["Christian Life","christian-life/"],["Personal Crisis","christian-life/personal-crisis-christian-life/"],["Relating To God","relationships/relating-to-god-relationships/"]],
    "date": [2010,11,22],
    "passage": "Romans 8:18-30",
    "quote": "2 Corinthians 4:17",
    "tags": [["comfort","comfort"],["His will","his-will"],["joy","joy"],["suffering","suffering"],["trials","trials"]],
    "title": "Storm Clouds And Blue Sky",
    "url": "http://odb.org/2010/11/22/storm-clouds-and-blue-sky/"
  }, 
  { "author": ["David H. Roper","davidhroper"],
    "categories": [["Archives","christian-life/archives-christian-life/"],["Attitudes","christian-life/attitudes-christian-life/"],["Christian Life","christian-life/"],["Relating To God","relationships/relating-to-god-relationships/"]],
    "date": [2010,11,21],
    "passage": "Psalm 8:1-2",
    "quote": "Psalm 8:2",
    "tags": [["children","children"],["christian faith","christian-faith"],["parenting","parenting"],["praise","praise"]],
    "title": "Out Of The Mouth Of Babes",
    "url": "http://odb.org/2010/11/21/out-of-the-mouth-of-babes/"
  }, 
  { "author": ["C. P. Hia","cphia"],
    "categories": [["Archives","christian-life/archives-christian-life/"],["Basics Of Faith","basics-of-faith/"],["Christian Life","christian-life/"],["God","basics-of-faith/god-basics-of-faith/"],["Personal Crisis","christian-life/personal-crisis-christian-life/"]],
    "date": [2010,11,20],
    "passage": "Romans 6:1-14",
    "quote": "Romans 6:11",
    "tags": [["cross","cross"],["power for living","power-for-living"],["salvation","salvation"],["sin","sin-christian-life"],["temptation","temptation"]],
    "title": "Misapplied Learning",
    "url": "http://odb.org/2010/11/20/misapplied-learning/"
  }, 
  { "author": ["Joe Stowell","joestowell"],
    "categories": [["Archives","christian-life/archives-christian-life/"],["Basics Of Faith","basics-of-faith/"],["Christian Life","christian-life/"],["Relating To God","relationships/relating-to-god-relationships/"]],
    "date": [2010,11,19],
    "passage": "1 Peter 2:9-17",
    "quote": "1 Peter 2:9",
    "tags": [["christlikeness","christlikeness"],["holiness","holiness"],["human governments","human-governments"],["loyalty","loyalty"],["purity","purity"]],
    "title": "National Pride",
    "url": "http://odb.org/2010/11/19/national-pride/"
  }, 
  { "author": ["Dennis Fisher","dennisfisher"],
    "categories": [["Archives","christian-life/archives-christian-life/"],["Basics Of Faith","basics-of-faith/"],["Christian Life","christian-life/"],["God","basics-of-faith/god-basics-of-faith/"]],
    "date": [2010,11,18],
    "passage": "Hebrews 13:1-9",
    "quote": "Hebrews 13:9",
    "tags": [["Bible","bible"],["meditation","meditation"],["memorization","memorization"],["reading","reading"],["truth vs. error","truth-vs-error"]],
    "title": "Spiritual Junk Food",
    "url": "http://odb.org/2010/11/18/spiritual-junk-food/"
  }, 
  { "author": ["Albert Lee","albertlee"],
    "categories": [["Archives","christian-life/archives-christian-life/"],["Basics Of Faith","basics-of-faith/"],["Character","christian-life/character-christian-life/"],["Christian Life","christian-life/"],["God","basics-of-faith/god-basics-of-faith/"]],
    "date": [2010,11,17],
    "passage": "2 Timothy 2:20-22",
    "quote": "1 John 3:10",
    "tags": [["christian faith","christian-faith"],["cross","cross"],["growth","growth"],["Jesus Christ","jesus-christ"],["resurrection","resurrection"],["righteousness","righteousness"]],
    "title": "Say No And Yes",
    "url": "http://odb.org/2010/11/17/say-no-and-yes/"
  }, 
  { "author": ["David C. McCasland","davidcmccasland"],
    "categories": [["Archives","christian-life/archives-christian-life/"],["Character","christian-life/character-christian-life/"],["Christian Life","christian-life/"],["Relating To God","relationships/relating-to-god-relationships/"]],
    "date": [2010,11,16],
    "passage": "2 Timothy 2:3-16",
    "quote": "2 Timothy 2:15",
    "tags": [["christlikeness","christlikeness"],["faithfulness","faithfulness"],["integrity","integrity"],["obedience","obedience"],["perseverance","perseverance"],["work","work"]],
    "title": "Daily Diligence",
    "url": "http://odb.org/2010/11/16/daily-diligence/"
  }, 
  { "author": ["Dave Branon","davebranon"],
    "categories": [["Archives","christian-life/archives-christian-life/"],["Christian Life","christian-life/"],["Ministry & Outreach","ministry-and-outreach/"],["Relating To God","relationships/relating-to-god-relationships/"],["Relationships","relationships/"]],
    "date": [2010,11,15],
    "passage": "Mark 2:13-17",
    "quote": "Mark 2:15",
    "tags": [["christlikeness","christlikeness"],["love for others","love-for-others"],["missions","missions"],["sharing the gospel","sharing-the-gospel"],["witness","witness"]],
    "title": "Cross The Divide",
    "url": "http://odb.org/2010/11/15/cross-the-divide/"
  }, 
  { "author": ["Bill Crowder","billcrowder"],
    "categories": [["Archives","christian-life/archives-christian-life/"],["Christian Life","christian-life/"],["God","basics-of-faith/god-basics-of-faith/"],["Ministry & Outreach","ministry-and-outreach/"],["Personal Crisis","christian-life/personal-crisis-christian-life/"],["Relationships","relationships/"]],
    "date": [2010,11,14],
    "passage": "Philippians 1:12-20",
    "quote": "2 Timothy 3:12",
    "tags": [["christlikeness","christlikeness"],["compassion","compassion"],["persecution","persecution"],["sharing the gospel","sharing-the-gospel"],["suffering","suffering"]],
    "title": "No Laughing Matter",
    "url": "http://odb.org/2010/11/14/no-laughing-matter/"
  }, 
  { "author": ["Cindy Hess Kasper","cindyhesskasper"],
    "categories": [["Archives","christian-life/archives-christian-life/"],["Attitudes","christian-life/attitudes-christian-life/"],["Basics Of Faith","basics-of-faith/"],["Christian Life","christian-life/"],["Relating To God","relationships/relating-to-god-relationships/"]],
    "date": [2010,11,13],
    "passage": "Psalm 139:1-16",
    "quote": "Psalm 139:15",
    "tags": [["cost of","cost-of"],["God's love","gods-love"],["self-images","self-images"],["significance","significance"]],
    "title": "Significant",
    "url": "http://odb.org/2010/11/13/significant/"
  }, 
  { "author": ["Marvin Williams","marvinwilliams"],
    "categories": [["Archives","christian-life/archives-christian-life/"],["Attitudes","christian-life/attitudes-christian-life/"],["Christian Life","christian-life/"],["Relating To God","relationships/relating-to-god-relationships/"]],
    "date": [2010,11,12],
    "passage": "John 6:25-36",
    "quote": "John 6:26",
    "tags": [["christlikeness","christlikeness"],["eternal life","eternal-life"],["fellowship with","fellowship-with"],["Jesus Christ","jesus-christ"],["salvation","salvation"]],
    "title": "More Than Loaves",
    "url": "http://odb.org/2010/11/12/more-than-loaves/"
  }, 
  { "author": ["Mart De Haan","martdehaan"],
    "categories": [["Archives","christian-life/archives-christian-life/"],["Character","christian-life/character-christian-life/"],["Christian Life","christian-life/"],["Personal Crisis","christian-life/personal-crisis-christian-life/"],["Relationships","relationships/"]],
    "date": [2010,11,11],
    "passage": "Philippians 2:20-30",
    "quote": "Philippians 2:30",
    "tags": [["His love","his-love"],["love for","love-for"],["love for others","love-for-others"],["selfless","selfless"]],
    "title": "Selfless Love",
    "url": "http://odb.org/2010/11/11/selfless-love-2/"
  }, 
  { "author": ["Anne Cetas","annecetas"],
    "categories": [["Archives","christian-life/archives-christian-life/"],["Attitudes","christian-life/attitudes-christian-life/"],["Christian Life","christian-life/"],["Personal Crisis","christian-life/personal-crisis-christian-life/"],["Relating To God","relationships/relating-to-god-relationships/"]],
    "date": [2010,11,10],
    "passage": "Luke 11:1-10",
    "quote": "Psalm 120:1",
    "tags": [["forgiveness from","forgiveness-from"],["Jesus Christ","jesus-christ"],["life example","life-example"],["prayer","prayer"],["quiet time","quiet-time"]],
    "title": "Where Do I Start?",
    "url": "http://odb.org/2010/11/10/where-do-i-start/"
  }, 
  { "author": ["Dennis Fisher","dennisfisher"],
    "categories": [["Archives","christian-life/archives-christian-life/"],["Character","christian-life/character-christian-life/"],["Christian Life","christian-life/"],["Relating To God","relationships/relating-to-god-relationships/"]],
    "date": [2010,11,9],
    "passage": "1 Cor. 9:24-27",
    "quote": "Galatians 5:22-23",
    "tags": [["christlikeness","christlikeness"],["fruit of the Spirit","fruit-of-the-spirit"],["Holy Spirit","holy-spirit"],["self-control","self-control"]],
    "title": "A Special Virtue",
    "url": "http://odb.org/2010/11/09/a-special-virtue/"
  }, 
  { "author": ["Dave Branon","davebranon"],
    "categories": [["Archives","christian-life/archives-christian-life/"],["Basics Of Faith","basics-of-faith/"],["Character","christian-life/character-christian-life/"],["Christian Life","christian-life/"],["Relating To God","relationships/relating-to-god-relationships/"]],
    "date": [2010,11,8],
    "passage": "Hebrews 5:12–6:3",
    "quote": "2 Corinthians 13:11",
    "tags": [["christlikeness","christlikeness"],["growth","growth"],["sanctification","sanctification"]],
    "title": "Aim High",
    "url": "http://odb.org/2010/11/08/aim-high/"
  }, 
  { "author": ["Joe Stowell","joestowell"],
    "categories": [["Archives","christian-life/archives-christian-life/"],["Basics Of Faith","basics-of-faith/"],["Christian Life","christian-life/"],["Ministry & Outreach","ministry-and-outreach/"],["Relating To God","relationships/relating-to-god-relationships/"]],
    "date": [2010,11,7],
    "passage": "Colossians 1:9-14",
    "quote": "Colossians 1:10",
    "tags": [["body of Christ","body-of-christ"],["christian faith","christian-faith"],["christlikeness","christlikeness"],["Church","church-basics-of-faith"],["presence","presence"]],
    "title": "God’s Presence At Church",
    "url": "http://odb.org/2010/11/07/god%e2%80%99s-presence-at-church/"
  }, 
  { "author": ["David C. McCasland","davidcmccasland"],
    "categories": [["Archives","christian-life/archives-christian-life/"],["Attitudes","christian-life/attitudes-christian-life/"],["Character","christian-life/character-christian-life/"],["Christian Life","christian-life/"]],
    "date": [2010,11,6],
    "passage": "Hebrews 3:7-15",
    "quote": "Hebrews 3:13",
    "tags": [["obedience","obedience"],["procrastination","procrastination"],["sin","sin-christian-life"],["temptation","temptation"]],
    "title": "Do It Now!",
    "url": "http://odb.org/2010/11/06/do-it-now/"
  }, 
  { "author": ["Bill Crowder","billcrowder"],
    "categories": [["Archives","christian-life/archives-christian-life/"],["Character","christian-life/character-christian-life/"],["Christian Life","christian-life/"],["Ministry & Outreach","ministry-and-outreach/"],["Relating To God","relationships/relating-to-god-relationships/"]],
    "date": [2010,11,5],
    "passage": "Matthew 5:13-20",
    "quote": "Matthew 5:16",
    "tags": [["grace","grace"],["legacy","legacy"],["presence","presence"],["testimony","testimony"]],
    "title": "A Lasting Imprint",
    "url": "http://odb.org/2010/11/05/a-lasting-imprint/"
  }, 
  { "author": ["Julie Ackerman Link","julieackermanlink"],
    "categories": [["Archives","christian-life/archives-christian-life/"],["Attitudes","christian-life/attitudes-christian-life/"],["Character","christian-life/character-christian-life/"],["Christian Life","christian-life/"],["Relating To God","relationships/relating-to-god-relationships/"]],
    "date": [2010,11,4],
    "passage": "2 Kings 5:1-15",
    "quote": "2 Kings 5:15",
    "tags": [["guidance","guidance"],["humility","humility"],["leading","leading"],["serving","serving"]],
    "title": "Remember John",
    "url": "http://odb.org/2010/11/04/remember-john/"
  }, 
  { "author": ["Dennis Fisher","dennisfisher"],
    "categories": [["Archives","christian-life/archives-christian-life/"],["Christian Life","christian-life/"],["Personal Crisis","christian-life/personal-crisis-christian-life/"],["Relating To God","relationships/relating-to-god-relationships/"]],
    "date": [2010,11,3],
    "passage": "Psalm 30:6-12",
    "quote": "Psalm 30:6",
    "tags": [["adversity","adversity"],["gratitude","gratitude"],["self-sufficiency","self-sufficiency"],["thankfulness","thankfulness"],["trials","trials"]],
    "title": "It Can Never Happen To Me",
    "url": "http://odb.org/2010/11/03/it-can-never-happen-to-me/"
  }, 
  { "author": ["Marvin Williams","marvinwilliams"],
    "categories": [["Archives","christian-life/archives-christian-life/"],["Attitudes","christian-life/attitudes-christian-life/"],["Christian Life","christian-life/"],["Relating To God","relationships/relating-to-god-relationships/"],["Relationships","relationships/"]],
    "date": [2010,11,2],
    "passage": "Luke 10:25-37",
    "quote": "Luke 10:33",
    "tags": [["compassion","compassion"],["kindness","kindness"],["love for","love-for"],["love for others","love-for-others"]],
    "title": "Neighborly Kindness",
    "url": "http://odb.org/2010/11/02/neighborly-kindness/"
  }, 
  { "author": ["Jennifer Benson Schuldt","jenniferbschuldt"],
    "categories": [["Archives","christian-life/archives-christian-life/"],["Attitudes","christian-life/attitudes-christian-life/"],["Christian Life","christian-life/"],["Relating To God","relationships/relating-to-god-relationships/"]],
    "date": [2010,11,1],
    "passage": "Ecclesiastes 5:8-17",
    "quote": "Ecclesiastes 5:16",
    "tags": [["eternity","eternity"],["heaven","heaven"],["money","money"],["possessions","possessions"]],
    "title": "Stockpiling Or Storing?",
    "url": "http://odb.org/2010/11/01/stockpiling-or-storing/"
  }
],
"month": 11,
"year": 2010
}